{
  "gitSyncId": "627cff875072600e7a34bc9b_627d95e65072600e7a34bd08",
  "id": "Recipe Type_GetRecipeUnit1",
  "pluginId": "restapi-plugin",
  "pluginType": "API",
  "unpublishedAction": {
    "actionConfiguration": {
      "autoGeneratedHeaders": [
        {
          "key": "content-type",
          "value": "application/json"
        }
      ],
      "body": "{\"scode_type\":RRS_Weight_Unit}",
      "encodeParamsToggle": true,
      "formData": {
        "apiContentType": "application/json"
      },
      "headers": [],
      "httpMethod": "POST",
      "paginationType": "NONE",
      "path": "",
      "pluginSpecifiedTemplates": [
        {
          "value": true
        }
      ],
      "queryParameters": [],
      "timeoutInMillisecond": 100000
    },
    "confirmBeforeExecute": false,
    "datasource": {
      "datasourceConfiguration": {
        "url": "{{appsmith.store.baseurl}}/recipeSet/getSourceCode"
      },
      "isAutoGenerated": false,
      "name": "DEFAULT_REST_DATASOURCE",
      "pluginId": "restapi-plugin"
    },
    "dynamicBindingPathList": [
      {
        "key": "datasourceUrl"
      }
    ],
    "executeOnLoad": true,
    "name": "GetRecipeUnit1",
    "pageId": "Recipe Type",
    "userSetOnLoad": false
  }
}