{
    "boxShadow": "none",
    "widgetName": "Text217Copy1Copy2",
    "displayName": "Text",
    "iconSVG": "/static/media/icon.97c59b52.svg",
    "topRow": 8,
    "bottomRow": 13,
    "type": "TEXT_WIDGET",
    "hideCard": false,
    "animateLoading": true,
    "dynamicTriggerPathList": [],
    "overflow": "NONE",
    "fontFamily": "System Default",
    "leftColumn": 1,
    "dynamicBindingPathList": [{"key": "text"}],
    "truncateButtonColor": "#FFC13D",
    "text": "{{appsmith.store.MassUpdateRecipeErrMsg}}",
    "key": "x0kxuyzhrv",
    "labelTextSize": "0.875rem",
    "rightColumn": 64,
    "textAlign": "LEFT",
    "dynamicHeight": "FIXED",
    "widgetId": "3ohz277qg0",
    "isVisible": true,
    "fontStyle": "BOLD",
    "textColor": "#231F20",
    "version": 1,
    "parentId": "2ab2zjh5a5",
    "renderMode": "CANVAS",
    "isLoading": false,
    "borderRadius": "0px",
    "maxDynamicHeight": 9000,
    "fontSize": "1rem",
    "minDynamicHeight": 4
}