{
    "widgetName": "lblMachine",
    "displayName": "Text",
    "iconSVG": "/formbuilderui/static/media/icon.97c59b523e6f70ba6f40a10fc2c7c5b5.svg",
    "searchTags": [
        "typography",
        "paragraph",
        "label"
    ],
    "topRow": 0,
    "bottomRow": 5,
    "parentRowSpace": 10,
    "type": "TEXT_WIDGET",
    "hideCard": false,
    "shouldScrollContents": true,
    "animateLoading": true,
    "overflow": "NONE",
    "fontFamily": "{{appsmith.theme.fontFamily.appFont}}",
    "parentColumnSpace": 13.640625,
    "dynamicTriggerPathList": [],
    "leftColumn": 0,
    "dynamicBindingPathList": [
        {"key": "text"},
        {"key": "fontFamily"}
    ],
    "shouldTruncate": false,
    "truncateButtonColor": "#FFC13D",
    "text": "Machine Group:<br><b>{{appsmith.store.ResourceGroupDropDownName}}<\/b>",
    "key": "dmbgfqckaf",
    "isDeprecated": false,
    "rightColumn": 11,
    "textAlign": "LEFT",
    "dynamicHeight": "AUTO_HEIGHT",
    "widgetId": "4nvoa6absa",
    "isVisible": true,
    "fontStyle": "",
    "textColor": "#231F20",
    "version": 1,
    "parentId": "37sldjznnw",
    "renderMode": "CANVAS",
    "isLoading": false,
    "originalTopRow": 0,
    "borderRadius": "{{appsmith.theme.borderRadius.appBorderRadius}}",
    "maxDynamicHeight": 9000,
    "originalBottomRow": 5,
    "fontSize": "0.875rem",
    "minDynamicHeight": 4
}