{
  "animateLoading": true,
  "borderRadius": "0px",
  "bottomRow": 43,
  "boxShadow": "none",
  "canEscapeKeyClose": true,
  "canOutsideClickClose": true,
  "children": [
    {
      "borderRadius": "0px",
      "bottomRow": 780,
      "boxShadow": "none",
      "canExtend": true,
      "detachFromLayout": true,
      "displayName": "Canvas",
      "dynamicBindingPathList": [],
      "dynamicTriggerPathList": [],
      "hideCard": true,
      "isDisabled": false,
      "isLoading": false,
      "isVisible": true,
      "key": "fzwt2r73w8",
      "labelTextSize": "0.875rem",
      "leftColumn": 0,
      "minHeight": 782,
      "parentColumnSpace": 1,
      "parentId": "bg0sodl2wg",
      "parentRowSpace": 1,
      "renderMode": "CANVAS",
      "rightColumn": 430.5,
      "shouldScrollContents": false,
      "topRow": 0,
      "type": "CANVAS_WIDGET",
      "version": 1,
      "widgetId": "8ltycp54pp",
      "widgetName": "Canvas5"
    }
  ],
  "detachFromLayout": true,
  "displayName": "Modal",
  "dynamicBindingPathList": [],
  "dynamicHeight": "FIXED",
  "dynamicTriggerPathList": [],
  "height": 782,
  "hideCard": false,
  "iconSVG": "/static/media/icon.4975978e.svg",
  "isCanvas": true,
  "isLoading": false,
  "key": "iwalbzltyo",
  "labelTextSize": "0.875rem",
  "leftColumn": 9,
  "maxDynamicHeight": 9000,
  "minDynamicHeight": 4,
  "parentColumnSpace": 17.9375,
  "parentId": "0",
  "parentRowSpace": 10,
  "renderMode": "CANVAS",
  "rightColumn": 33,
  "shouldScrollContents": false,
  "topRow": 19,
  "type": "MODAL_WIDGET",
  "version": 2,
  "widgetId": "bg0sodl2wg",
  "widgetName": "ProductGroupModal",
  "width": 934
}