{
  "gitSyncId": "636e155fe60d44705cd472c4_636e176de60d44705cd47426",
  "id": "MassUpdate_IsModificNoExist",
  "pluginId": "restapi-plugin",
  "pluginType": "API",
  "unpublishedAction": {
    "actionConfiguration": {
      "autoGeneratedHeaders": [
        {
          "key": "content-type",
          "value": "application/json"
        }
      ],
      "body": "{\n\t\"modifNo\":{{Number(ModificationNumberSearch.text.trim())}}\n}",
      "encodeParamsToggle": true,
      "formData": {
        "apiContentType": "none"
      },
      "headers": [],
      "httpMethod": "POST",
      "paginationType": "NONE",
      "path": "",
      "pluginSpecifiedTemplates": [
        {
          "value": true
        }
      ],
      "queryParameters": [],
      "timeoutInMillisecond": 10000
    },
    "confirmBeforeExecute": false,
    "datasource": {
      "datasourceConfiguration": {
        "url": "{{appsmith.store.baseurl}}/modifnumber/is-exist"
      },
      "isAutoGenerated": false,
      "name": "DEFAULT_REST_DATASOURCE",
      "pluginId": "restapi-plugin"
    },
    "dynamicBindingPathList": [
      {
        "key": "path"
      },
      {
        "key": "queryParameters[0].value"
      },
      {
        "key": "datasourceUrl"
      },
      {
        "key": "body"
      }
    ],
    "executeOnLoad": false,
    "name": "IsModificNoExist",
    "pageId": "MassUpdate",
    "userSetOnLoad": false
  }
}