{
  "accentColor": "{{appsmith.theme.colors.primaryColor}}",
  "allowCurrencyChange": false,
  "animateLoading": true,
  "autoFocus": false,
  "borderRadius": "0px",
  "bottomRow": 8,
  "boxShadow": "none",
  "defaultText": "{{(Number(appsmith.store.calculatedField.sv_tdc)==0?'':Number(appsmith.store.calculatedField.sv_tdc).toFixed(2))}} ",
  "displayName": "Input",
  "dynamicBindingPathList": [
    {
      "key": "defaultText"
    },
    {
      "key": "isVisible"
    }
  ],
  "dynamicPropertyPathList": [
    {
      "key": "isVisible"
    }
  ],
  "dynamicTriggerPathList": [],
  "hideCard": false,
  "iconAlign": "left",
  "iconSVG": "/static/media/icon.9f505595.svg",
  "inputType": "TEXT",
  "isDisabled": true,
  "isLoading": false,
  "isRequired": false,
  "isVisible": "{{appsmith.store.RecipeClassDropDown==\"PD\" || appsmith.store.RecipeClassDropDown==\"RM\" || appsmith.store.RecipeClassDropDown==\"CO\"}}",
  "key": "i3jdc2ee61",
  "label": "",
  "labelStyle": "",
  "labelTextSize": "0.875rem",
  "leftColumn": 9,
  "parentColumnSpace": 17.625,
  "parentId": "5mu8z3bkjc",
  "parentRowSpace": 10,
  "renderMode": "CANVAS",
  "resetOnSubmit": true,
  "rightColumn": 14,
  "topRow": 4,
  "type": "INPUT_WIDGET",
  "version": 1,
  "widgetId": "cgsw414e4t",
  "widgetName": "DryContentInPerInput"
}