{
    "boxShadow": "none",
    "widgetName": "GradeTextCopy",
    "dynamicPropertyPathList": [{"key": "fontSize"}],
    "displayName": "Text",
    "iconSVG": "/static/media/icon.97c59b52.svg",
    "topRow": 0,
    "bottomRow": 4,
    "type": "TEXT_WIDGET",
    "hideCard": false,
    "animateLoading": true,
    "dynamicTriggerPathList": [],
    "overflow": "NONE",
    "fontFamily": "System Default",
    "leftColumn": 15,
    "dynamicBindingPathList": [],
    "truncateButtonColor": "#FFC13D",
    "text": "Grade",
    "key": "6beh96atob",
    "labelTextSize": "0.875rem",
    "rightColumn": 25,
    "textAlign": "LEFT",
    "dynamicHeight": "FIXED",
    "widgetId": "52hfykwnw6",
    "isVisible": true,
    "fontStyle": "BOLD",
    "textColor": "#1F1F1F",
    "version": 1,
    "parentId": "6xx905l89q",
    "renderMode": "CANVAS",
    "isLoading": false,
    "borderRadius": "0px",
    "maxDynamicHeight": 9000,
    "fontSize": "0.75rem",
    "minDynamicHeight": 4
}