{
  "gitSyncId": "64acf15cc1f57807de253b78_64c24124c1f57807de25a210",
  "id": "CreateRecipePU_TabulatorSetup.getHtml",
  "pluginId": "js-plugin",
  "pluginType": "JS",
  "unpublishedAction": {
    "actionConfiguration": {
      "encodeParamsToggle": true,
      "isAsync": false,
      "jsArguments": [],
      "paginationType": "NONE",
      "timeoutInMillisecond": 10000
    },
    "collectionId": "CreateRecipePU_TabulatorSetup",
    "confirmBeforeExecute": false,
    "datasource": {
      "isAutoGenerated": false,
      "name": "UNUSED_DATASOURCE",
      "pluginId": "js-plugin"
    },
    "dynamicBindingPathList": [
      {
        "key": "body"
      }
    ],
    "executeOnLoad": false,
    "fullyQualifiedName": "TabulatorSetup.getHtml",
    "name": "getHtml",
    "pageId": "CreateRecipePU",
    "userSetOnLoad": false
  }
}