{
    "boxShadow": "none",
    "widgetName": "Text17",
    "displayName": "Text",
    "iconSVG": "/static/media/icon.97c59b52.svg",
    "topRow": 15,
    "bottomRow": 19,
    "parentRowSpace": 10,
    "type": "TEXT_WIDGET",
    "hideCard": false,
    "animateLoading": true,
    "parentColumnSpace": 12,
    "dynamicTriggerPathList": [],
    "overflow": "NONE",
    "fontFamily": "System Default",
    "leftColumn": 1,
    "dynamicBindingPathList": [],
    "truncateButtonColor": "#FFC13D",
    "text": "Product List",
    "key": "oz0qcdrbzb",
    "labelTextSize": "0.875rem",
    "rightColumn": 8,
    "textAlign": "LEFT",
    "dynamicHeight": "FIXED",
    "widgetId": "1wxztjq5xm",
    "isVisible": true,
    "fontStyle": "BOLD",
    "textColor": "#231F20",
    "version": 1,
    "parentId": "t50hzb8coy",
    "renderMode": "CANVAS",
    "isLoading": false,
    "borderRadius": "0px",
    "maxDynamicHeight": 9000,
    "fontSize": "0.875rem",
    "minDynamicHeight": 4
}