{
    "widgetName": "lblRevno",
    "displayName": "Text",
    "iconSVG": "/static/media/icon.97c59b523e6f70ba6f40a10fc2c7c5b5.svg",
    "searchTags": [
        "typography",
        "paragraph",
        "label"
    ],
    "topRow": 0,
    "bottomRow": 6,
    "parentRowSpace": 10,
    "type": "TEXT_WIDGET",
    "hideCard": false,
    "shouldScrollContents": true,
    "animateLoading": true,
    "overflow": "NONE",
    "fontFamily": "{{appsmith.theme.fontFamily.appFont}}",
    "parentColumnSpace": 19.4375,
    "dynamicTriggerPathList": [],
    "leftColumn": 29,
    "dynamicBindingPathList": [
        {"key": "truncateButtonColor"},
        {"key": "fontFamily"},
        {"key": "borderRadius"},
        {"key": "text"}
    ],
    "shouldTruncate": false,
    "truncateButtonColor": "{{appsmith.theme.colors.primaryColor}}",
    "text": "Rev. No.:<br><b>{{GetProductionRecipeForView.data.REVISION_NO}}<\/b>",
    "key": "lo0ty8t5y0",
    "isDeprecated": false,
    "rightColumn": 32,
    "textAlign": "LEFT",
    "dynamicHeight": "AUTO_HEIGHT",
    "widgetId": "bj7ik2m898",
    "minWidth": 450,
    "isVisible": true,
    "fontStyle": "",
    "textColor": "#231F20",
    "version": 1,
    "parentId": "tokuhz327h",
    "renderMode": "CANVAS",
    "isLoading": false,
    "responsiveBehavior": "fill",
    "originalTopRow": 0,
    "borderRadius": "{{appsmith.theme.borderRadius.appBorderRadius}}",
    "maxDynamicHeight": 9000,
    "originalBottomRow": 8,
    "fontSize": "0.875rem",
    "minDynamicHeight": 4
}