{
  "gitSyncId": "64e30e9b77d28b0f1ab4548a_6508051177d28b0f1ab50089",
  "id": "CreateRecipeRM_GetModifStatus",
  "pluginId": "restapi-plugin",
  "pluginType": "API",
  "unpublishedAction": {
    "actionConfiguration": {
      "autoGeneratedHeaders": [
        {
          "key": "content-type",
          "value": "application/json"
        }
      ],
      "body": "{\n  \"modifNo\": {{Number(appsmith.store.modificNo)}}\n}",
      "bodyFormData": [],
      "encodeParamsToggle": true,
      "formData": {
        "apiContentType": "application/json"
      },
      "headers": [],
      "httpMethod": "POST",
      "paginationType": "NONE",
      "path": "",
      "pluginSpecifiedTemplates": [
        {
          "value": true
        }
      ],
      "queryParameters": [],
      "timeoutInMillisecond": 10000
    },
    "confirmBeforeExecute": false,
    "datasource": {
      "datasourceConfiguration": {
        "url": "{{appsmith.store.baseurl}}/modifnumber/status"
      },
      "isAutoGenerated": false,
      "name": "DEFAULT_REST_DATASOURCE",
      "pluginId": "restapi-plugin"
    },
    "dynamicBindingPathList": [
      {
        "key": "body"
      },
      {
        "key": "datasourceUrl"
      }
    ],
    "executeOnLoad": false,
    "name": "GetModifStatus",
    "pageId": "CreateRecipeRM",
    "userSetOnLoad": false
  }
}