{
  "gitSyncId": "62e95e33d04c4f3c9d2dde51_62f95b4821e1b462dea147f1",
  "id": "CreateRecipe_SetPropertyUnit.FunctionCodeInput",
  "pluginId": "js-plugin",
  "pluginType": "JS",
  "unpublishedAction": {
    "actionConfiguration": {
      "encodeParamsToggle": true,
      "isAsync": false,
      "jsArguments": [],
      "paginationType": "NONE",
      "timeoutInMillisecond": 10000
    },
    "collectionId": "CreateRecipe_SetPropertyUnit",
    "confirmBeforeExecute": false,
    "datasource": {
      "isAutoGenerated": false,
      "name": "UNUSED_DATASOURCE",
      "pluginId": "js-plugin"
    },
    "dynamicBindingPathList": [
      {
        "key": "body"
      }
    ],
    "executeOnLoad": false,
    "fullyQualifiedName": "SetPropertyUnit.FunctionCodeInput",
    "name": "FunctionCodeInput",
    "pageId": "CreateRecipe",
    "userSetOnLoad": false
  }
}