{
    "boxShadow": "none",
    "iconSVG": "/static/media/icon.9f505595da61a34f563dba82adeb06ec.svg",
    "topRow": 4,
    "labelWidth": 5,
    "type": "INPUT_WIDGET_V2",
    "animateLoading": true,
    "resetOnSubmit": false,
    "leftColumn": 0,
    "dynamicBindingPathList": [{"key": "accentColor"}],
    "labelStyle": "",
    "inputType": "MULTI_LINE_TEXT",
    "isDisabled": false,
    "isRequired": false,
    "dynamicHeight": "FIXED",
    "accentColor": "{{appsmith.theme.colors.primaryColor}}",
    "showStepArrows": false,
    "isVisible": true,
    "version": 2,
    "isLoading": false,
    "borderRadius": "0px",
    "mobileBottomRow": 11,
    "widgetName": "CostExpectedImpactText",
    "displayName": "Input",
    "searchTags": [
        "form",
        "text input",
        "number",
        "textarea"
    ],
    "bottomRow": 18,
    "parentRowSpace": 10,
    "autoFocus": false,
    "hideCard": false,
    "mobileRightColumn": 11.999999999999998,
    "parentColumnSpace": 10.894726562499999,
    "dynamicTriggerPathList": [],
    "labelPosition": "Top",
    "key": "3ckurtrtxx",
    "labelTextSize": "0.875rem",
    "isDeprecated": false,
    "rightColumn": 64,
    "widgetId": "18orjyzz7n",
    "minWidth": 450,
    "label": "",
    "parentId": "4zox7ctr22",
    "labelAlignment": "left",
    "renderMode": "CANVAS",
    "mobileTopRow": 4,
    "responsiveBehavior": "fill",
    "mobileLeftColumn": 0,
    "maxDynamicHeight": 9000,
    "shouldAllowAutofill": false,
    "iconAlign": "left",
    "defaultText": "",
    "minDynamicHeight": 4
}