{
    "boxShadow": "none",
    "widgetName": "UpdateModifSHEQTabs",
    "isCanvas": true,
    "dynamicPropertyPathList": [
        {"key": "tabsObj.tab1.isVisible"},
        {"key": "tabsObj.tab2.isVisible"},
        {"key": "tabsObj.tabavi99p7w08.isVisible"},
        {"key": "tabsObj.tabqtbv4www1u.isVisible"},
        {"key": "tabsObj.tab9epquqr3ok.isVisible"},
        {"key": "tabsObj.tabvk0g1vb7gz.isVisible"},
        {"key": "isVisible"}
    ],
    "displayName": "Tabs",
    "iconSVG": "/static/media/icon.74a6d653.svg",
    "topRow": 22,
    "bottomRow": 55,
    "parentRowSpace": 10,
    "type": "TABS_WIDGET",
    "hideCard": false,
    "shouldScrollContents": true,
    "animateLoading": true,
    "parentColumnSpace": 17.3125,
    "dynamicTriggerPathList": [],
    "leftColumn": 1,
    "dynamicBindingPathList": [
        {"key": "tabsObj.tab9epquqr3ok.isVisible"},
        {"key": "tabsObj.tabqtbv4www1u.isVisible"},
        {"key": "tabsObj.tabavi99p7w08.isVisible"},
        {"key": "tabsObj.tab2.isVisible"},
        {"key": "tabsObj.tab1.isVisible"},
        {"key": "accentColor"},
        {"key": "tabsObj.tabvk0g1vb7gz.isVisible"},
        {"key": "isVisible"}
    ],
    "children": [
        {
            "tabId": "tab1",
            "boxShadow": "none",
            "widgetName": "Canvas5Copy",
            "displayName": "Canvas",
            "topRow": 0,
            "bottomRow": 290,
            "parentRowSpace": 1,
            "type": "CANVAS_WIDGET",
            "canExtend": true,
            "hideCard": true,
            "shouldScrollContents": false,
            "minHeight": 400,
            "parentColumnSpace": 1,
            "dynamicTriggerPathList": [],
            "leftColumn": 0,
            "dynamicBindingPathList": [],
            "isDisabled": false,
            "key": "w4wakc7z66",
            "labelTextSize": "0.875rem",
            "tabName": "Safety - S",
            "rightColumn": 415.5,
            "detachFromLayout": true,
            "widgetId": "0qjqf0efjy",
            "isVisible": true,
            "version": 1,
            "parentId": "nba4hunyq5",
            "renderMode": "CANVAS",
            "isLoading": false,
            "borderRadius": "0px"
        },
        {
            "tabId": "tab2",
            "boxShadow": "none",
            "widgetName": "Canvas6Copy",
            "displayName": "Canvas",
            "topRow": 0,
            "bottomRow": 290,
            "parentRowSpace": 1,
            "type": "CANVAS_WIDGET",
            "canExtend": true,
            "hideCard": true,
            "shouldScrollContents": false,
            "minHeight": 400,
            "parentColumnSpace": 1,
            "dynamicTriggerPathList": [],
            "leftColumn": 0,
            "dynamicBindingPathList": [],
            "isDisabled": false,
            "key": "w4wakc7z66",
            "labelTextSize": "0.875rem",
            "tabName": "Health - H",
            "rightColumn": 415.5,
            "detachFromLayout": true,
            "widgetId": "yjspjjno55",
            "isVisible": true,
            "version": 1,
            "parentId": "nba4hunyq5",
            "renderMode": "CANVAS",
            "isLoading": false,
            "borderRadius": "0px"
        },
        {
            "tabId": "tabavi99p7w08",
            "boxShadow": "none",
            "widgetName": "Canvas7Copy",
            "displayName": "Canvas",
            "topRow": 1,
            "bottomRow": 290,
            "parentRowSpace": 1,
            "type": "CANVAS_WIDGET",
            "canExtend": false,
            "hideCard": true,
            "minHeight": 190,
            "parentColumnSpace": 1,
            "dynamicTriggerPathList": [],
            "leftColumn": 0,
            "dynamicBindingPathList": [],
            "key": "w4wakc7z66",
            "labelTextSize": "0.875rem",
            "tabName": "Environment - E",
            "rightColumn": 1073.375,
            "detachFromLayout": true,
            "widgetId": "qq9mfgvmei",
            "containerStyle": "none",
            "isVisible": true,
            "version": 1,
            "parentId": "nba4hunyq5",
            "renderMode": "CANVAS",
            "isLoading": false,
            "borderRadius": "0px"
        },
        {
            "tabId": "tabqtbv4www1u",
            "boxShadow": "none",
            "widgetName": "Canvas8Copy",
            "displayName": "Canvas",
            "topRow": 1,
            "bottomRow": 290,
            "parentRowSpace": 1,
            "type": "CANVAS_WIDGET",
            "canExtend": false,
            "hideCard": true,
            "minHeight": 190,
            "parentColumnSpace": 1,
            "dynamicTriggerPathList": [],
            "leftColumn": 0,
            "dynamicBindingPathList": [],
            "key": "w4wakc7z66",
            "labelTextSize": "0.875rem",
            "tabName": "Quality - Q",
            "rightColumn": 1073.375,
            "detachFromLayout": true,
            "widgetId": "cq1fnc651g",
            "containerStyle": "none",
            "isVisible": true,
            "version": 1,
            "parentId": "nba4hunyq5",
            "renderMode": "CANVAS",
            "isLoading": false,
            "borderRadius": "0px"
        },
        {
            "tabId": "tab9epquqr3ok",
            "boxShadow": "none",
            "widgetName": "Canvas9Copy",
            "displayName": "Canvas",
            "topRow": 1,
            "bottomRow": 290,
            "parentRowSpace": 1,
            "type": "CANVAS_WIDGET",
            "canExtend": false,
            "hideCard": true,
            "minHeight": 190,
            "parentColumnSpace": 1,
            "dynamicTriggerPathList": [],
            "leftColumn": 0,
            "dynamicBindingPathList": [],
            "key": "w4wakc7z66",
            "labelTextSize": "0.875rem",
            "tabName": "Hygiene - HY",
            "rightColumn": 1073.375,
            "detachFromLayout": true,
            "widgetId": "1n03xuz5hj",
            "containerStyle": "none",
            "isVisible": true,
            "version": 1,
            "parentId": "nba4hunyq5",
            "renderMode": "CANVAS",
            "isLoading": false,
            "borderRadius": "0px"
        },
        {
            "tabId": "tabvk0g1vb7gz",
            "mobileBottomRow": 331,
            "widgetName": "Canvas14",
            "displayName": "Canvas",
            "topRow": 1,
            "bottomRow": 290,
            "parentRowSpace": 1,
            "type": "CANVAS_WIDGET",
            "canExtend": false,
            "hideCard": true,
            "minHeight": 330,
            "mobileRightColumn": 1073.375,
            "parentColumnSpace": 1,
            "dynamicTriggerPathList": [],
            "leftColumn": 0,
            "dynamicBindingPathList": [],
            "key": "c2dc59q3ll",
            "isDeprecated": false,
            "tabName": "Cost - C",
            "rightColumn": 1073.375,
            "detachFromLayout": true,
            "widgetId": "0ipycjvlj3",
            "containerStyle": "none",
            "minWidth": 450,
            "isVisible": true,
            "version": 1,
            "parentId": "nba4hunyq5",
            "renderMode": "CANVAS",
            "isLoading": false,
            "mobileTopRow": 1,
            "responsiveBehavior": "fill",
            "mobileLeftColumn": 0,
            "flexLayers": []
        }
    ],
    "key": "mkl7jcez4w",
    "labelTextSize": "0.875rem",
    "rightColumn": 63,
    "dynamicHeight": "AUTO_HEIGHT",
    "widgetId": "nba4hunyq5",
    "accentColor": "{{appsmith.theme.colors.primaryColor}}",
    "defaultTab": "",
    "shouldShowTabs": true,
    "tabsObj": {
        "tab9epquqr3ok": {
            "widgetId": "1n03xuz5hj",
            "index": 4,
            "id": "tab9epquqr3ok",
            "label": "Hygiene - HY",
            "isVisible": "{{SHEQMultiSelect.selectedOptionValues.includes('HY')}}"
        },
        "tabavi99p7w08": {
            "widgetId": "qq9mfgvmei",
            "index": 2,
            "id": "tabavi99p7w08",
            "label": "Environment - E",
            "isVisible": "{{SHEQMultiSelect.selectedOptionValues.includes('E')}}"
        },
        "tabqtbv4www1u": {
            "widgetId": "cq1fnc651g",
            "index": 3,
            "id": "tabqtbv4www1u",
            "label": "Quality - Q",
            "isVisible": "{{SHEQMultiSelect.selectedOptionValues.includes('Q')}}"
        },
        "tab1": {
            "widgetId": "0qjqf0efjy",
            "index": 0,
            "label": "Safety - S",
            "id": "tab1",
            "isVisible": "{{SHEQMultiSelect.selectedOptionValues.includes('S')}}"
        },
        "tab2": {
            "widgetId": "yjspjjno55",
            "index": 1,
            "label": "Health - H",
            "id": "tab2",
            "isVisible": "{{SHEQMultiSelect.selectedOptionValues.includes('H')}}"
        },
        "tabvk0g1vb7gz": {
            "widgetId": "0ipycjvlj3",
            "index": 5,
            "id": "tabvk0g1vb7gz",
            "label": "Cost - C",
            "isVisible": "{{SHEQMultiSelect.selectedOptionValues.includes('C')}}"
        }
    },
    "isVisible": "{{SHEQMultiSelect.selectedOptionValues.length > 0}}",
    "version": 3,
    "parentId": "j68pfsw7no",
    "renderMode": "CANVAS",
    "isLoading": false,
    "originalTopRow": 22,
    "borderRadius": "0px",
    "maxDynamicHeight": 9000,
    "originalBottomRow": 55,
    "minDynamicHeight": 10
}