{
  "accentColor": "{{appsmith.theme.colors.primaryColor}}",
  "animateLoading": true,
  "autoFocus": false,
  "borderRadius": "0px",
  "bottomRow": 8,
  "boxShadow": "none",
  "defaultText": "{{BindDropDown.InterMediateCodeDefault()}}",
  "displayName": "Input",
  "dynamicBindingPathList": [
    {
      "key": "isDisabled"
    },
    {
      "key": "accentColor"
    },
    {
      "key": "defaultText"
    }
  ],
  "dynamicHeight": "FIXED",
  "dynamicPropertyPathList": [
    {
      "key": "isDisabled"
    },
    {
      "key": "onBlur"
    }
  ],
  "dynamicTriggerPathList": [
    {
      "key": "onBlur"
    }
  ],
  "hideCard": false,
  "iconAlign": "left",
  "iconSVG": "/formbuilderui/static/media/icon.9f505595da61a34f563dba82adeb06ec.svg",
  "inputType": "TEXT",
  "isDeprecated": false,
  "isDisabled": "{{BindDropDown.DisableInterMatCodeInput()}}",
  "isLoading": false,
  "isRequired": false,
  "isVisible": true,
  "key": "nkpufffh1d",
  "label": "",
  "labelAlignment": "left",
  "labelPosition": "Top",
  "labelStyle": "BOLD",
  "labelTextColor": "#000000",
  "labelTextSize": "0.875rem",
  "labelWidth": 5,
  "leftColumn": 47,
  "maxDynamicHeight": 9000,
  "minDynamicHeight": 4,
  "onBlur": "{{storeValue(\"RecipeList_InterMaterial\",InterMatCodeInput.text,true);TabulatorAction.EmptyTabulator();}}",
  "parentColumnSpace": 13.953125,
  "parentId": "t482q159hb",
  "parentRowSpace": 10,
  "renderMode": "CANVAS",
  "resetOnSubmit": true,
  "rightColumn": 52,
  "searchTags": [
    "form",
    "text input",
    "number",
    "textarea"
  ],
  "topRow": 4,
  "type": "INPUT_WIDGET_V2",
  "version": 2,
  "widgetId": "877ix767yt",
  "widgetName": "InterMatCodeInput"
}