{
  "animateLoading": true,
  "backgroundColor": "",
  "borderRadius": "0px",
  "bottomRow": 131,
  "boxShadow": "none",
  "canEscapeKeyClose": true,
  "canOutsideClickClose": false,
  "children": [
    {
      "accentColor": "{{appsmith.theme.colors.primaryColor}}",
      "borderRadius": "{{appsmith.theme.borderRadius.appBorderRadius}}",
      "bottomRow": 620,
      "boxShadow": "none",
      "canExtend": true,
      "detachFromLayout": true,
      "displayName": "Canvas",
      "dynamicBindingPathList": [
        {
          "key": "borderRadius"
        },
        {
          "key": "accentColor"
        }
      ],
      "dynamicTriggerPathList": [],
      "hideCard": true,
      "isDeprecated": false,
      "isDisabled": false,
      "isLoading": false,
      "isVisible": true,
      "key": "itc4vxqtbv",
      "leftColumn": 0,
      "minHeight": 620,
      "parentColumnSpace": 1,
      "parentId": "lm8yasvdwy",
      "parentRowSpace": 1,
      "renderMode": "CANVAS",
      "rightColumn": 334.875,
      "shouldScrollContents": false,
      "topRow": 0,
      "type": "CANVAS_WIDGET",
      "version": 1,
      "widgetId": "7fnxk5boes",
      "widgetName": "Canvas14Copy"
    }
  ],
  "detachFromLayout": true,
  "displayName": "Modal",
  "dynamicBindingPathList": [],
  "dynamicHeight": "FIXED",
  "dynamicTriggerPathList": [],
  "height": 620,
  "hideCard": false,
  "iconSVG": "/formbuilderui/static/media/icon.4975978e9a961fb0bfb4e38de7ecc7c5.svg",
  "isCanvas": true,
  "isDeprecated": false,
  "isLoading": false,
  "key": "6rh4zfsjmp",
  "leftColumn": 20,
  "maxDynamicHeight": 9000,
  "minDynamicHeight": 4,
  "parentColumnSpace": 13.953125,
  "parentId": "0",
  "parentRowSpace": 10,
  "renderMode": "CANVAS",
  "rightColumn": 44,
  "searchTags": [
    "dialog",
    "popup",
    "notification"
  ],
  "shouldScrollContents": false,
  "topRow": 107,
  "type": "MODAL_WIDGET",
  "version": 2,
  "widgetId": "lm8yasvdwy",
  "widgetName": "CreateRecipeComparasionModal",
  "width": 859.75
}