{
  "gitSyncId": "63b8e4261d5a9a20e2673655_63c05524f7db535996d62ac2",
  "id": "MassUpdate_GetFilteredRecipeView",
  "pluginId": "restapi-plugin",
  "pluginType": "API",
  "unpublishedAction": {
    "actionConfiguration": {
      "autoGeneratedHeaders": [
        {
          "key": "content-type",
          "value": "application/json"
        }
      ],
      "body": "{\n\t\"recipeNumber\":{{ProductFilterSelect.selectedOptionValue == \"\" ?Number(RecipeTable.triggeredRow.RECIPE_NUMBER) : Number(RecipeByProductFilter.triggeredRow.RECIPE_NUMBER)}},\n\t\"recipeSetNumber\":{{Number(appsmith.store.RecipeSetNumber)}}\n}",
      "bodyFormData": [],
      "encodeParamsToggle": true,
      "formData": {
        "apiContentType": "application/json"
      },
      "headers": [],
      "httpMethod": "POST",
      "paginationType": "NONE",
      "path": "",
      "pluginSpecifiedTemplates": [
        {
          "value": true
        }
      ],
      "queryParameters": [],
      "timeoutInMillisecond": 10000
    },
    "confirmBeforeExecute": false,
    "datasource": {
      "datasourceConfiguration": {
        "url": "{{appsmith.store.baseurl}}/recipe/getfilteredforview"
      },
      "isAutoGenerated": false,
      "name": "DEFAULT_REST_DATASOURCE",
      "pluginId": "restapi-plugin"
    },
    "dynamicBindingPathList": [
      {
        "key": "path"
      },
      {
        "key": "queryParameters[0].value"
      },
      {
        "key": "queryParameters[1].value"
      },
      {
        "key": "datasourceUrl"
      },
      {
        "key": "body"
      }
    ],
    "executeOnLoad": false,
    "name": "GetFilteredRecipeView",
    "pageId": "MassUpdate",
    "userSetOnLoad": true
  }
}